{
  "SRA": {
    "SAMPLE_SET": {"SAMPLE": {
      "@alias": "05_23_006_2-sc-2013-10-16T09:23:23Z-1720503",
      "@accession": "ERS360272",
      "@center_name": "The Wellcome Trust Sanger Institute",
      "IDENTIFIERS": {
        "PRIMARY_ID": {"_$": "ERS360272"},
        "EXTERNAL_ID": {
          "@namespace": "BioSample",
          "_$": "SAMEA2223875"
        },
        "SUBMITTER_ID": [
          {
            "@namespace": "SC",
            "_$": "05_23_006_2-sc-2013-10-16T09:23:23Z-1720503"
          },
          {
            "@namespace": "The Wellcome Trust Sanger Institute",
            "_$": "05_23_006_2-sc-2013-10-16T09:23:23Z-1720503"
          }
        ]
      },
      "TITLE": {"_$": "Escherichia coli"},
      "SAMPLE_NAME": {
        "COMMON_NAME": {"_$": "Escherichia coli"},
        "TAXON_ID": {"_$": "562"},
        "SCIENTIFIC_NAME": {"_$": "Escherichia coli"}
      },
      "SAMPLE_ATTRIBUTES": {"SAMPLE_ATTRIBUTE": [
        {
          "TAG": {"_$": "Strain"},
          "VALUE": {}
        },
        {
          "TAG": {"_$": "Sample Description"},
          "VALUE": {}
        },
        {
          "TAG": {"_$": "ArrayExpress-Phenotype"},
          "VALUE": {"_$": "N/A"}
        },
        {
          "TAG": {"_$": "ArrayExpress-Species"},
          "VALUE": {"_$": "Escherichia coli"}
        }
      ]}
    }},
    "SUBMISSION": {
      "@accession": "ERA258346",
      "@center_name": "SC",
      "@broker_name": "",
      "@alias": "05_23_006_2-sc-2013-10-16T09:23:23Z-1720503",
      "@lab_name": ""
    }
  },
  "_@default": "",
  "_@xml": "http://www.w3.org/XML/1998/namespace"
}
